pyncp/__init__.py
pyncp/answer.py
pyncp/core.py
pyncp/request.py
pyncp/slip.py
pyncp/utils.py
ul_pyncp-1.0.5.dist-info/LICENSE
ul_pyncp-1.0.5.dist-info/METADATA
ul_pyncp-1.0.5.dist-info/WHEEL
ul_pyncp-1.0.5.dist-info/top_level.txt
ul_pyncp-1.0.5.dist-info/RECORD
