Metadata-Version: 2.1
Name: ul-pyncp
Version: 1.0.5
Summary: Python pyncp library
Home-page: UNKNOWN
License: MIT
Platform: any
Classifier: Intended Audience :: Developers
Classifier: License :: OSI Approved :: MIT License
Classifier: Programming Language :: Python
Classifier: Programming Language :: Python :: 3.6
Classifier: Programming Language :: Python :: 3.7
Classifier: Programming Language :: Python :: 3.8
Classifier: Programming Language :: Python :: 3.9
Classifier: Operating System :: OS Independent
License-File: LICENSE
